g42cloudsdkcts/__init__.py
g42cloudsdkcts/v3/__init__.py
g42cloudsdkcts/v3/cts_async_client.py
g42cloudsdkcts/v3/cts_client.py
g42cloudsdkcts/v3/model/__init__.py
g42cloudsdkcts/v3/model/base_user.py
g42cloudsdkcts/v3/model/create_notification_request.py
g42cloudsdkcts/v3/model/create_notification_request_body.py
g42cloudsdkcts/v3/model/create_notification_response.py
g42cloudsdkcts/v3/model/create_tracker_request.py
g42cloudsdkcts/v3/model/create_tracker_request_body.py
g42cloudsdkcts/v3/model/create_tracker_response.py
g42cloudsdkcts/v3/model/data_bucket.py
g42cloudsdkcts/v3/model/data_bucket_query.py
g42cloudsdkcts/v3/model/delete_notification_request.py
g42cloudsdkcts/v3/model/delete_notification_response.py
g42cloudsdkcts/v3/model/delete_tracker_request.py
g42cloudsdkcts/v3/model/delete_tracker_response.py
g42cloudsdkcts/v3/model/filter.py
g42cloudsdkcts/v3/model/list_notifications_request.py
g42cloudsdkcts/v3/model/list_notifications_response.py
g42cloudsdkcts/v3/model/list_quotas_request.py
g42cloudsdkcts/v3/model/list_quotas_response.py
g42cloudsdkcts/v3/model/list_traces_request.py
g42cloudsdkcts/v3/model/list_traces_response.py
g42cloudsdkcts/v3/model/list_trackers_request.py
g42cloudsdkcts/v3/model/list_trackers_response.py
g42cloudsdkcts/v3/model/lts.py
g42cloudsdkcts/v3/model/meta_data.py
g42cloudsdkcts/v3/model/notification_users.py
g42cloudsdkcts/v3/model/notifications_response_body.py
g42cloudsdkcts/v3/model/obs_info.py
g42cloudsdkcts/v3/model/operations.py
g42cloudsdkcts/v3/model/quota.py
g42cloudsdkcts/v3/model/traces.py
g42cloudsdkcts/v3/model/tracker_obs_info.py
g42cloudsdkcts/v3/model/tracker_response_body.py
g42cloudsdkcts/v3/model/update_notification_request.py
g42cloudsdkcts/v3/model/update_notification_request_body.py
g42cloudsdkcts/v3/model/update_notification_response.py
g42cloudsdkcts/v3/model/update_tracker_request.py
g42cloudsdkcts/v3/model/update_tracker_request_body.py
g42cloudsdkcts/v3/model/update_tracker_response.py
g42cloudsdkcts-0.0.10b0.dist-info/LICENSE
g42cloudsdkcts-0.0.10b0.dist-info/METADATA
g42cloudsdkcts-0.0.10b0.dist-info/WHEEL
g42cloudsdkcts-0.0.10b0.dist-info/top_level.txt
g42cloudsdkcts-0.0.10b0.dist-info/RECORD
